cdp/__init__.py
cdp/cdp.py
cdp/ciholas_serial_number.py
cdp/device_data_items.py
cdp/data_items/__init__.py
cdp/data_items/data_items.py
cdp_py-1.7.1.dist-info/METADATA
cdp_py-1.7.1.dist-info/WHEEL
cdp_py-1.7.1.dist-info/top_level.txt
cdp_py-1.7.1.dist-info/RECORD
