Metadata-Version: 2.1
Name: cdp-py
Version: 1.7.1
Summary: Ciholas Data Protocol
Home-page: https://github.com/ciholas/cdp-py
Author: Ciholas, Inc.
Author-email: cuwb.support@ciholas.com
License: CC BY 4.0
Keywords: cdp ciholas data protocol
Platform: UNKNOWN
Classifier: Programming Language :: Python :: 3
Classifier: Operating System :: OS Independent
Requires-Python: >=3
